jaxfmm/__init__.py
jaxfmm/basis.py
jaxfmm/debug_helpers.py
jaxfmm/fmm.py
jaxfmm/hierarchy.py
jaxfmm/pbc.py
jaxfmm/rotation.py
jaxfmm/transf.py
jaxfmm-0.1.1.dist-info/METADATA
jaxfmm-0.1.1.dist-info/WHEEL
jaxfmm-0.1.1.dist-info/licenses/LICENSE
jaxfmm-0.1.1.dist-info/RECORD
