Metadata-Version: 2.4
Name: jaxFMM
Version: 0.1.1
Summary: Adaptive Fast Multipole Method with Laplace kernel in JAX.
Project-URL: Homepage, https://gitlab.com/jaxfmm/jaxfmm
Author-email: Robert Kraft <robert.kraft@univie.ac.at>
License: MIT License
License-File: LICENSE
Keywords: FMM,N-body,jax,potential,treecode
Classifier: Development Status :: 3 - Alpha
Classifier: Intended Audience :: Science/Research
Classifier: License :: OSI Approved :: MIT License
Classifier: Topic :: Scientific/Engineering :: Physics
Requires-Python: >=3.9
Requires-Dist: jax
Provides-Extra: cuda
Requires-Dist: jax[cuda]; extra == 'cuda'
Provides-Extra: dev
Requires-Dist: numpy; extra == 'dev'
Requires-Dist: pytest; extra == 'dev'
Requires-Dist: pyvista; extra == 'dev'
